sap/__init__.py
sap/instance_manager/__init__.py
sap/instance_manager/adapter.py
sap/instance_manager/constants.py
sap/instance_manager/lru_cache.py
sap/instance_manager/manager.py
sap/instance_manager/polling_util.py
sap/instance_manager/user_input.py
sap_instance_manager-0.4.2.data/data/CHANGELOG.rst
sap_instance_manager-0.4.2.data/data/version.txt
sap_instance_manager-0.4.2.dist-info/LICENSE
sap_instance_manager-0.4.2.dist-info/METADATA
sap_instance_manager-0.4.2.dist-info/WHEEL
sap_instance_manager-0.4.2.dist-info/top_level.txt
sap_instance_manager-0.4.2.dist-info/RECORD
