Metadata-Version: 2.1
Name: sap-instance-manager
Version: 0.4.2
Summary: SAP Python instance manager client
Home-page: https://www.sap.com/
Author: SAP SE
License: SAP DEVELOPER LICENSE AGREEMENT
Keywords: SAP instancemanager
Platform: UNKNOWN
Classifier: Development Status :: 5 - Production/Stable
Classifier: Intended Audience :: Developers
Classifier: Operating System :: OS Independent
Classifier: Programming Language :: Python :: 3.4
Classifier: Programming Language :: Python :: 3.5
Classifier: Programming Language :: Python :: 3.6
Classifier: Programming Language :: Python :: 3.7
Classifier: Programming Language :: Python :: 3.8
Classifier: Topic :: Software Development
Classifier: Topic :: Software Development :: Libraries :: Python Modules
Requires-Python: >=3.0
Requires-Dist: requests (==2.26.0)
Requires-Dist: jsonschema (==3.2.0)
